LICENSE
README.md
setup.cfg
setup.py
cuco/Config.py
cuco/ModuleName.py
cuco/__init__.py
cuco/__main__.py
cuco/constants.py
cuco/exception.py
cuco/expansion.py
cuco.egg-info/PKG-INFO
cuco.egg-info/SOURCES.txt
cuco.egg-info/dependency_links.txt
cuco.egg-info/requires.txt
cuco.egg-info/top_level.txt
cuco/utils/__init__.py
cuco/utils/file.py
cuco/utils/string.py
test/test_config_object_creation.py
test/test_flat_config_expansion.py
test/test_loading.py
test/test_module_name_handling.py
test/test_nested_config_expansion.py