Metadata-Version: 2.1
Name: cuco
Version: 0.9.0
Summary: Project for making it easier to write configuration files which may be automatically converted into a set of alternative system setups
Home-page: https://github.com/zeionara/cuco
Author: Zeio Nara
Author-email: zeionara@gmail.com
License: UNKNOWN
Platform: UNKNOWN
Classifier: Programming Language :: Python :: 3.9
License-File: LICENSE
